<?xml version="1.0" encoding="UTF-8"?>
<list>
	<item id="14712" name="Cow Hair Accessory">
		<for>
		</for>
	</item>
	<item id="14746" name="Refined Chick Hat">
		<for>
		</for>
	</item>
	<item id="14747" name="Refined Black Feather Mask">
		<for>
		</for>
	</item>
	<item id="14748" name="Refined Carnival Circlet">
		<for>
		</for>
	</item>
	<item id="14749" name="Afro Perm Wig">
		<for>
		</for>
	</item>
	<item id="14750" name="Bamboo Hat">
		<for>
		</for>
	</item>
	<item id="14751" name="Smart Glasses">
		<for>
		</for>
	</item>
	<item id="14752" name="For Events - Refined Medieval Style Party Mask">
		<for />
	</item>
	<item id="14753" name="Shadow Item - Refined Chick Hat - Escape">
		<for />
	</item>
	<item id="14754" name="Shadow Item - Refined Chick Hat - Big Head">
		<for />
	</item>
	<item id="14755" name="Shadow Item - Refined Chick Hat - Firework">
		<for />
	</item>
	<item id="14756" name="Shadow Item - Refined Black Feather Mask - Escape">
		<for />
	</item>
	<item id="14757" name="Shadow Item - Refined Black Feather Mask - Big Head">
		<for />
	</item>
	<item id="14758" name="Shadow Item - Refined Black Feather Mask - Firework">
		<for />
	</item>
	<item id="14759" name="Shadow Item - Refined Carnival Circlet - Escape">
		<for />
	</item>
	<item id="14760" name="Shadow Item - Refined Carnival Circlet - Big Head">
		<for />
	</item>
	<item id="14761" name="Shadow Item - Refined Carnival Circlet - Firework">
		<for />
	</item>
	<item id="14762" name="Shadow Item - Refined Medieval Style Party Mask - Escape">
		<for />
	</item>
	<item id="14763" name="Shadow Item - Refined Medieval Style Party Mask - Big Head">
		<for />
	</item>
	<item id="14764" name="Shadow Item - Refined Medieval Style Party Mask - Firework">
		<for />
	</item>
	<item id="14771" name="Kat the Cat Hat - 14 day limited period">
		<for />
	</item>
	<item id="14772" name="Coronet">
		<for />
	</item>
	<item id="14773" name="Suit - 14 day limited period">
		<for />
	</item>
	<item id="14775" name="Agathion Seal Bracelet - Love - 14 day limited period">
		<for />
	</item>
	<item id="14776" name="Agathion Seal Bracelet - Juju - 14 day limited period">
		<for />
	</item>
	<item id="14796" name="Baguette's Sigil">
		<for />
	</item>
	<item id="14798" name="Afro Perm Wig - Black">
		<for />
	</item>
	<item id="14799" name="Afro Perm Wig - Gold">
		<for />
	</item>
</list>