<?xml version="1.0" encoding="UTF-8"?>
<list xmlns:xsi="http://www.w3.org/2001/XMLSchema-instance" xsi:noNamespaceSchemaLocation="../xsd/buylist.xsd">
	<item id="58" /> <!-- Mithril Breastplate -->
	<item id="59" /> <!-- Mithril Gaiters -->
	<item id="47" /> <!-- Helmet -->
	<item id="628" /> <!-- Hoplon -->
	<item id="352" /> <!-- Brigandine Tunic -->
	<item id="2378" /> <!-- Brigandine Gaiters -->
	<item id="2411" /> <!-- Brigandine Helmet -->
	<item id="2493" /> <!-- Brigandine Shield -->
	<item id="394" /> <!-- Reinforced Leather Shirt -->
	<item id="416" /> <!-- Reinforced Leather Gaiters -->
	<item id="2422" /> <!-- Reinforced Leather Boots -->
	<item id="395" /> <!-- Manticore Skin Shirt -->
	<item id="417" /> <!-- Manticore Skin Gaiters -->
	<item id="2424" /> <!-- Manticore Skin Boots -->
	<item id="436" /> <!-- Tunic of Knowledge -->
	<item id="469" /> <!-- Stockings of Knowledge -->
	<item id="2447" /> <!-- Gloves of Knowledge -->
	<item id="437" /> <!-- Mithril Tunic -->
	<item id="470" /> <!-- Mithril Stockings -->
	<item id="2450" /> <!-- Mithril Gloves -->
</list>
