<?xml version="1.0" encoding="UTF-8"?>
<list xmlns:xsi="http://www.w3.org/2001/XMLSchema-instance" xsi:noNamespaceSchemaLocation="../xsd/buylist.xsd">
	<item id="2052" /> <!-- Mithril Dagger Blade -->
	<item id="2053" /> <!-- Scallop Jamadhr Edge -->
	<item id="2054" /> <!-- Light Crossbow Shaft -->
	<item id="2055" /> <!-- Glaive Edge -->
	<item id="2056" /> <!-- Vajra Wand Frame -->
	<item id="2057" /> <!-- Ancient Reagent Remnant -->
	<item id="2058" /> <!-- Atuba Mace Head -->
	<item id="2059" /> <!-- Flamberge Blade -->
	<item id="2060" /> <!-- Stormbringer Blade -->
	<item id="2061" /> <!-- Big Hammer Head -->
	<item id="2062" /> <!-- Scythe Edge -->
	<item id="2063" /> <!-- Battle Axe Head -->
	<item id="2064" /> <!-- Silver Axe Head -->
	<item id="2065" /> <!-- Skull Graver Head -->
	<item id="2066" /> <!-- Heavy Doom Hammer Head -->
	<item id="2067" /> <!-- Crystal Staff Head -->
	<item id="2068" /> <!-- Stick of Faith Shaft -->
	<item id="2069" /> <!-- Heavy Doom Axe Blade -->
	<item id="2070" /> <!-- Cursed Dagger Blade -->
	<item id="2071" /> <!-- Wolverine Needle Edge -->
	<item id="2072" /> <!-- Dark Elven Dagger Edge -->
	<item id="2073" /> <!-- Chakram Edge -->
	<item id="2074" /> <!-- Crystallized Ice Bow Shaft -->
	<item id="2075" /> <!-- Orcish Glaive Blade -->
	<item id="2076" /> <!-- Body Slasher Blade -->
	<item id="2077" /> <!-- Shamshir Blade -->
	<item id="2078" /> <!-- Katana Blade -->
	<item id="2079" /> <!-- Bec De Corbin Blade -->
	<item id="2080" /> <!-- Spirit Sword Blade -->
	<item id="2081" /> <!-- Raid Sword Blade -->
	<item id="2082" /> <!-- Cursed Staff Head -->
	<item id="2083" /> <!-- Stiletto Edge -->
	<item id="2084" /> <!-- Soulfire Dirk Blade -->
	<item id="2085" /> <!-- Crossbow Shaft -->
	<item id="2086" /> <!-- Noble Elven Bow Shaft -->
	<item id="2087" /> <!-- Tears of Fairy Drop -->
	<item id="2088" /> <!-- Horn of Glory Fragment -->
	<item id="2089" /> <!-- Caliburs Edge -->
	<item id="2090" /> <!-- Delusional Blade -->
	<item id="2091" /> <!-- Tsurugi Blade -->
	<item id="2092" /> <!-- Homunkulus's Sword Blade -->
	<item id="2093" /> <!-- Poleaxe Blade -->
	<item id="2094" /> <!-- Sword of Limit Blade -->
	<item id="2095" /> <!-- Sword of Nightmare Blade -->
	<item id="2096" /> <!-- Sword of Whispering Death Blade -->
	<item id="2097" /> <!-- War Axe Blade -->
	<item id="2098" /> <!-- Nirvana Axe Blade -->
	<item id="2099" /> <!-- Stick of Eternity Shaft -->
	<item id="2100" /> <!-- Paradia Staff Head -->
	<item id="2101" /> <!-- Inferno Staff Head -->
</list>
