<?xml version="1.0" encoding="UTF-8"?>
<skill id="227" levels="50" name="Light Armor Mastery">

  <table name="#pDef">
	4.2 5.3 6.5 7.7 9 9.9 10.8 12.7 13.7 14.8
	16.9 18 19.1 21.5 22.7 24 25.3 26.6 27.9
	29.3 30.7 32.1 33.6 35 36.5 38.1 39.6 41.2
	42.8 44.5 46.1 47.8 49.5 51.3 53.1 54.9
	58.6 60.5 64.4 66.4 70.5 72.6 76.9 79.1
	83.6 85.9 90.6 93.0 97.9 100.4
  </table>

  <table name="#rEvas">
	3 3 5 5 6 6 6 6 6 6 6 6 6 6 6 6 6 6 6 6
	6 6 6 6 6 6 6 6 6 6 6 6 6 6 7 7 7 7 7 7
	7 7 7 7 7 7 7 7 7 7
  </table>

  <set name="power" val="0.0"/>
  <set name="target" val="TARGET_SELF"/>
  <set name="skillType" val="BUFF"/>
  <set name="operateType" val="OP_PASSIVE"/>
  <set name="castRange" val="-1"/>
  <for>
    <add order="0x40" stat="pDef" val="#pDef">
      <and>
        <using kind="Light"/>
        <not>
<using kind="Heavy,Magic"/>
</not>
      </and>
    </add>
    <add order="0x40" stat="rEvas" val="#rEvas">
      <and>
        <using kind="Light"/>
        <not>
<using kind="Heavy,Magic"/>
</not>
      </and>
    </add>
  </for>

</skill>
