<?xml version='1.0' encoding='utf-8'?>
<list>
<skill id="21000" levels="1" name="Release Seal on Agathion - Majo">
  <set name="target" val="TARGET_NONE"/>
  <set name="skillType" val="NOTDONE"/>
  <set name="operateType" val="OP_PASSIVE"/>
  <set name="castRange" val="-1"/>
  <for>
  </for>
</skill>
<skill id="21001" levels="1" name="Release Seal on Agathion - Gold Majo">
  <set name="target" val="TARGET_NONE"/>
  <set name="skillType" val="NOTDONE"/>
  <set name="operateType" val="OP_PASSIVE"/>
  <set name="castRange" val="-1"/>
  <for>
  </for>
</skill>
<skill id="21002" levels="1" name="Release Seal on Agathion - Black Majo">
  <set name="target" val="TARGET_NONE"/>
  <set name="skillType" val="NOTDONE"/>
  <set name="operateType" val="OP_PASSIVE"/>
  <set name="castRange" val="-1"/>
  <for>
  </for>
</skill>
<skill id="21003" levels="1" name="Release Seal on Agathion - Plaipitak">
  <set name="target" val="TARGET_NONE"/>
  <set name="skillType" val="NOTDONE"/>
  <set name="operateType" val="OP_PASSIVE"/>
  <set name="castRange" val="-1"/>
  <for>
  </for>
</skill>
<skill id="21004" levels="1" name="Wind Walk">
  <set name="target" val="TARGET_NONE"/>
  <set name="skillType" val="NOTDONE"/>
  <set name="operateType" val="OP_PASSIVE"/>
  <set name="castRange" val="-1"/>
  <for>
  </for>
</skill>
<skill id="21005" levels="3" name="Agility">
  <set name="target" val="TARGET_NONE"/>
  <set name="skillType" val="NOTDONE"/>
  <set name="operateType" val="OP_PASSIVE"/>
  <set name="castRange" val="-1"/>
  <for>
  </for>
</skill>
<skill id="21006" levels="1" name="Large Firework Effect">
  <set name="target" val="TARGET_NONE"/>
  <set name="skillType" val="NOTDONE"/>
  <set name="operateType" val="OP_PASSIVE"/>
  <set name="castRange" val="-1"/>
  <for>
  </for>
</skill>
<skill id="21007" levels="1" name="Ability of Doubt">
  <set name="target" val="TARGET_NONE"/>
  <set name="skillType" val="NOTDONE"/>
  <set name="operateType" val="OP_PASSIVE"/>
  <set name="castRange" val="-1"/>
  <for>
  </for>
</skill>
</list>