<?xml version="1.0" encoding="UTF-8"?>
<skill id="4019" levels="1" name="Decrease Speed">

  <set name="save" val="5"/>
  <set name="power" val="0.0"/>
  <set name="target" val="TARGET_AREA"/>
  <set name="hitTime" val="1000"/>
  <set name="skillTime" val="2000"/>
  <set name="skillType" val="DEBUFF"/>
  <set name="operateType" val="OP_ACTIVE"/>
  <set name="buffDuration" val="120000"/>
  <set name="castRange" val="800"/>
 <!-- Done by dc -->

<table name="#Tab-runSpd"> 1.3 </table>
<for>
  <effect name="Buff" time="120" count="1" val="0">
    <div  order='0x50' stat='runSpd' val="#Tab-runSpd"/>
 </effect>
</for>


</skill>
