<?xml version="1.0" encoding="UTF-8"?>
<list>
	<item id="14682" name="Greater Elixir of Life (No-Grade)">
		<set name="shared_reuse_group" val="1" />
		<for />
	</item>
	<item id="14683" name="Greater Elixir of Life (D-Grade)">
		<set name="shared_reuse_group" val="2" />
		<for />
	</item>
	<item id="14684" name="Greater Elixir of Life (C-Grade)">
		<set name="shared_reuse_group" val="3" />
		<for />
	</item>
	<item id="14685" name="Greater Elixir of Life (B-Grade)">
		<set name="shared_reuse_group" val="4" />
		<for />
	</item>
	<item id="14686" name="Greater Elixir of Life (A-Grade)">
		<set name="shared_reuse_group" val="5" />
		<for />
	</item>
	<item id="14687" name="Greater Elixir of Life (S-Grade)">
		<set name="shared_reuse_group" val="6" />
		<for />
	</item>
	<item id="14688" name="Greater Elixir of Mental Strength (No-Grade)">
		<set name="shared_reuse_group" val="1" />
		<for />
	</item>
	<item id="14689" name="Greater Elixir of Mental Strength (D-Grade)">
		<set name="shared_reuse_group" val="2" />
		<for />
	</item>
	<item id="14690" name="Greater Elixir of Mental Strength (C-Grade)">
		<set name="shared_reuse_group" val="3" />
		<for />
	</item>
	<item id="14691" name="Greater Elixir of Mental Strength (B-Grade)">
		<set name="shared_reuse_group" val="4" />
		<for />
	</item>
	<item id="14692" name="Greater Elixir of Mental Strength (A-Grade)">
		<set name="shared_reuse_group" val="5" />
		<for />
	</item>
	<item id="14693" name="Greater Elixir of Mental Strength (S-Grade)">
		<set name="shared_reuse_group" val="6" />
		<for />
	</item>
	<item id="14694" name="Greater Elixir of CP (No Grade)">
		<set name="shared_reuse_group" val="7" />
		<for />
	</item>
	<item id="14695" name="Greater Elixir of CP (D-Grade)">
		<set name="shared_reuse_group" val="7" />
		<for />
	</item>
	<item id="14696" name="Greater Elixir of CP (C-Grade)">
		<set name="shared_reuse_group" val="7" />
		<for />
	</item>
	<item id="14697" name="Greater Elixir of CP (B-Grade)">
		<set name="shared_reuse_group" val="7" />
		<for />
	</item>
	<item id="14698" name="Greater Elixir of CP (A-Grade)">
		<set name="shared_reuse_group" val="7" />
		<for />
	</item>
	<item id="14699" name="Greater Elixir of CP (S-Grade)">
		<set name="shared_reuse_group" val="7" />
		<for />
	</item>
</list>